{
  "directed": false,
  "multigraph": false,
  "graph": {
    "name": "()_with_int_labels"
  },
  "nodes": [
    {
      "name": "Dakota",
      "id": 0
    },
    {
      "name": "Mountbatten",
      "id": 1
    },
    {
      "name": "Paya Lebar",
      "id": 2
    },
    {
      "name": "MacPherson",
      "id": 3
    },
    {
      "name": "Stadium",
      "id": 4
    },
    {
      "name": "Nicoll Highway",
      "id": 5
    },
    {
      "name": "Eunos",
      "id": 6
    },
    {
      "name": "Aljunied",
      "id": 7
    },
    {
      "name": "Kallang",
      "id": 8
    },
    {
      "name": "Bartley",
      "id": 9
    },
    {
      "name": "Lavender",
      "id": 10
    },
    {
      "name": "Tai Seng",
      "id": 11
    },
    {
      "name": "Soo Teck",
      "id": 12
    },
    {
      "name": "Cove",
      "id": 13
    },
    {
      "name": "Kranji",
      "id": 14
    },
    {
      "name": "Marsiling",
      "id": 15
    },
    {
      "name": "Yew Tee",
      "id": 16
    },
    {
      "name": "Woodlands",
      "id": 17
    },
    {
      "name": "Promenade",
      "id": 18
    },
    {
      "name": "Esplanade",
      "id": 19
    },
    {
      "name": "Bayfront",
      "id": 20
    },
    {
      "name": "Dhoby Ghaut",
      "id": 21
    },
    {
      "name": "Marina Bay",
      "id": 22
    },
    {
      "name": "Braddell",
      "id": 23
    },
    {
      "name": "Toa Payoh",
      "id": 24
    },
    {
      "name": "Bishan",
      "id": 25
    },
    {
      "name": "Meridian",
      "id": 26
    },
    {
      "name": "Coral Edge",
      "id": 27
    },
    {
      "name": "Oasis",
      "id": 28
    },
    {
      "name": "Punggol",
      "id": 29
    },
    {
      "name": "Damai",
      "id": 30
    },
    {
      "name": "Sengkang",
      "id": 31
    },
    {
      "name": "Sam Kee",
      "id": 32
    },
    {
      "name": "Kadaloor",
      "id": 33
    },
    {
      "name": "Riviera",
      "id": 34
    },
    {
      "name": "Nibong",
      "id": 35
    },
    {
      "name": "Buangkok",
      "id": 36
    },
    {
      "name": "Kovan",
      "id": 37
    },
    {
      "name": "Hougang",
      "id": 38
    },
    {
      "name": "Serangoon",
      "id": 39
    },
    {
      "name": "Woodleigh",
      "id": 40
    },
    {
      "name": "Rochor",
      "id": 41
    },
    {
      "name": "Little India",
      "id": 42
    },
    {
      "name": "Bugis",
      "id": 43
    },
    {
      "name": "Newton",
      "id": 44
    },
    {
      "name": "Stevens",
      "id": 45
    },
    {
      "name": "Downtown",
      "id": 46
    },
    {
      "name": "Buona Vista",
      "id": 47
    },
    {
      "name": "Holland Village",
      "id": 48
    },
    {
      "name": "one-north",
      "id": 49
    },
    {
      "name": "Commonwealth",
      "id": 50
    },
    {
      "name": "Dover",
      "id": 51
    },
    {
      "name": "Queenstown",
      "id": 52
    },
    {
      "name": "Clementi",
      "id": 53
    },
    {
      "name": "Redhill",
      "id": 54
    },
    {
      "name": "Labrador Park",
      "id": 55
    },
    {
      "name": "Telok Blangah",
      "id": 56
    },
    {
      "name": "Potong Pasir",
      "id": 57
    },
    {
      "name": "Boon Keng",
      "id": 58
    },
    {
      "name": "Farrer Park",
      "id": 59
    },
    {
      "name": "Clarke Quay",
      "id": 60
    },
    {
      "name": "Renjong",
      "id": 61
    },
    {
      "name": "Tongkang",
      "id": 62
    },
    {
      "name": "Layar",
      "id": 63
    },
    {
      "name": "Farmway",
      "id": 64
    },
    {
      "name": "Kangkar",
      "id": 65
    },
    {
      "name": "Ranggung",
      "id": 66
    },
    {
      "name": "Rumbia",
      "id": 67
    },
    {
      "name": "Bakau",
      "id": 68
    },
    {
      "name": "Compassvale",
      "id": 69
    },
    {
      "name": "Lorong Chuan",
      "id": 70
    },
    {
      "name": "Cheng Lim",
      "id": 71
    },
    {
      "name": "Fernvale",
      "id": 72
    },
    {
      "name": "HarbourFront",
      "id": 73
    },
    {
      "name": "Outram Park",
      "id": 74
    },
    {
      "name": "Chinatown",
      "id": 75
    },
    {
      "name": "Pasir Panjang",
      "id": 76
    },
    {
      "name": "Pasir Ris",
      "id": 77
    },
    {
      "name": "Tampines",
      "id": 78
    },
    {
      "name": "Simei",
      "id": 79
    },
    {
      "name": "Telok Ayer",
      "id": 80
    },
    {
      "name": "Bras Basah",
      "id": 81
    },
    {
      "name": "Haw Par Villa",
      "id": 82
    },
    {
      "name": "Botanic Gardens",
      "id": 83
    },
    {
      "name": "Farrer Road",
      "id": 84
    },
    {
      "name": "Caldecott",
      "id": 85
    },
    {
      "name": "Tan Kah Kee",
      "id": 86
    },
    {
      "name": "Sixth Avenue",
      "id": 87
    },
    {
      "name": "King Albert Park",
      "id": 88
    },
    {
      "name": "Bukit Batok",
      "id": 89
    },
    {
      "name": "Bukit Gombak",
      "id": 90
    },
    {
      "name": "Jurong East",
      "id": 91
    },
    {
      "name": "Pioneer",
      "id": 92
    },
    {
      "name": "Boon Lay",
      "id": 93
    },
    {
      "name": "Joo Koon",
      "id": 94
    },
    {
      "name": "Kupang",
      "id": 95
    },
    {
      "name": "Beauty World",
      "id": 96
    },
    {
      "name": "Cashew",
      "id": 97
    },
    {
      "name": "Hillview",
      "id": 98
    },
    {
      "name": "Bukit Panjang",
      "id": 99
    },
    {
      "name": "Marymount",
      "id": 100
    },
    {
      "name": "Yishun",
      "id": 101
    },
    {
      "name": "Khatib",
      "id": 102
    },
    {
      "name": "Sembawang",
      "id": 103
    },
    {
      "name": "Admiralty",
      "id": 104
    },
    {
      "name": "Kent Ridge",
      "id": 105
    },
    {
      "name": "Thanggam",
      "id": 106
    },
    {
      "name": "Choa Chu Kang",
      "id": 107
    },
    {
      "name": "City Hall",
      "id": 108
    },
    {
      "name": "Chinese Garden",
      "id": 109
    },
    {
      "name": "Lakeside",
      "id": 110
    },
    {
      "name": "Raffles Place",
      "id": 111
    },
    {
      "name": "Tanjong Pagar",
      "id": 112
    },
    {
      "name": "Marina South Pier",
      "id": 113
    },
    {
      "name": "Somerset",
      "id": 114
    },
    {
      "name": "Orchard",
      "id": 115
    },
    {
      "name": "Novena",
      "id": 116
    },
    {
      "name": "Tiong Bahru",
      "id": 117
    },
    {
      "name": "Keat Hong",
      "id": 118
    },
    {
      "name": "South View",
      "id": 119
    },
    {
      "name": "Phoenix",
      "id": 120
    },
    {
      "name": "Petir",
      "id": 121
    },
    {
      "name": "Senja",
      "id": 122
    },
    {
      "name": "Expo",
      "id": 123
    },
    {
      "name": "Changi Airport",
      "id": 124
    },
    {
      "name": "Tanah Merah",
      "id": 125
    },
    {
      "name": "Sumang",
      "id": 126
    },
    {
      "name": "Ang Mo Kio",
      "id": 127
    },
    {
      "name": "Yio Chu Kang",
      "id": 128
    },
    {
      "name": "Kembangan",
      "id": 129
    },
    {
      "name": "Teck Whye",
      "id": 130
    },
    {
      "name": "Jelapang",
      "id": 131
    },
    {
      "name": "Pending",
      "id": 132
    },
    {
      "name": "Bangkit",
      "id": 133
    },
    {
      "name": "Segar",
      "id": 134
    },
    {
      "name": "Fajar",
      "id": 135
    },
    {
      "name": "Ten Mile Junction",
      "id": 136
    },
    {
      "name": "Bedok",
      "id": 137
    }
  ],
  "links": [
    {
      "source": 0,
      "target": 1
    },
    {
      "source": 0,
      "target": 2
    },
    {
      "source": 0,
      "target": 3
    },
    {
      "source": 1,
      "target": 4
    },
    {
      "source": 1,
      "target": 5
    },
    {
      "source": 2,
      "target": 6
    },
    {
      "source": 2,
      "target": 7
    },
    {
      "source": 2,
      "target": 3
    },
    {
      "source": 2,
      "target": 8
    },
    {
      "source": 2,
      "target": 9
    },
    {
      "source": 2,
      "target": 10
    },
    {
      "source": 3,
      "target": 11
    },
    {
      "source": 4,
      "target": 5
    },
    {
      "source": 4,
      "target": 18
    },
    {
      "source": 5,
      "target": 18
    },
    {
      "source": 5,
      "target": 19
    },
    {
      "source": 5,
      "target": 20
    },
    {
      "source": 5,
      "target": 21
    },
    {
      "source": 5,
      "target": 22
    },
    {
      "source": 6,
      "target": 7
    },
    {
      "source": 6,
      "target": 129
    },
    {
      "source": 6,
      "target": 137
    },
    {
      "source": 6,
      "target": 10
    },
    {
      "source": 7,
      "target": 8
    },
    {
      "source": 7,
      "target": 43
    },
    {
      "source": 7,
      "target": 10
    },
    {
      "source": 7,
      "target": 108
    },
    {
      "source": 7,
      "target": 112
    },
    {
      "source": 8,
      "target": 10
    },
    {
      "source": 8,
      "target": 43
    },
    {
      "source": 8,
      "target": 108
    },
    {
      "source": 8,
      "target": 112
    },
    {
      "source": 9,
      "target": 39
    },
    {
      "source": 9,
      "target": 11
    },
    {
      "source": 10,
      "target": 43
    },
    {
      "source": 10,
      "target": 108
    },
    {
      "source": 10,
      "target": 112
    },
    {
      "source": 10,
      "target": 111
    },
    {
      "source": 10,
      "target": 119
    },
    {
      "source": 12,
      "target": 13
    },
    {
      "source": 12,
      "target": 35
    },
    {
      "source": 12,
      "target": 31
    },
    {
      "source": 13,
      "target": 26
    },
    {
      "source": 13,
      "target": 29
    },
    {
      "source": 13,
      "target": 33
    },
    {
      "source": 13,
      "target": 30
    },
    {
      "source": 13,
      "target": 35
    },
    {
      "source": 14,
      "target": 15
    },
    {
      "source": 14,
      "target": 16
    },
    {
      "source": 14,
      "target": 17
    },
    {
      "source": 15,
      "target": 16
    },
    {
      "source": 15,
      "target": 17
    },
    {
      "source": 16,
      "target": 107
    },
    {
      "source": 17,
      "target": 104
    },
    {
      "source": 18,
      "target": 41
    },
    {
      "source": 18,
      "target": 46
    },
    {
      "source": 18,
      "target": 19
    },
    {
      "source": 18,
      "target": 43
    },
    {
      "source": 18,
      "target": 20
    },
    {
      "source": 18,
      "target": 81
    },
    {
      "source": 18,
      "target": 42
    },
    {
      "source": 19,
      "target": 81
    },
    {
      "source": 19,
      "target": 21
    },
    {
      "source": 20,
      "target": 41
    },
    {
      "source": 20,
      "target": 46
    },
    {
      "source": 20,
      "target": 43
    },
    {
      "source": 20,
      "target": 22
    },
    {
      "source": 20,
      "target": 42
    },
    {
      "source": 21,
      "target": 59
    },
    {
      "source": 21,
      "target": 81
    },
    {
      "source": 21,
      "target": 60
    },
    {
      "source": 21,
      "target": 22
    },
    {
      "source": 21,
      "target": 42
    },
    {
      "source": 21,
      "target": 108
    },
    {
      "source": 21,
      "target": 114
    },
    {
      "source": 21,
      "target": 113
    },
    {
      "source": 22,
      "target": 113
    },
    {
      "source": 22,
      "target": 112
    },
    {
      "source": 22,
      "target": 111
    },
    {
      "source": 22,
      "target": 108
    },
    {
      "source": 22,
      "target": 114
    },
    {
      "source": 23,
      "target": 24
    },
    {
      "source": 23,
      "target": 25
    },
    {
      "source": 23,
      "target": 127
    },
    {
      "source": 24,
      "target": 25
    },
    {
      "source": 24,
      "target": 116
    },
    {
      "source": 25,
      "target": 100
    },
    {
      "source": 25,
      "target": 70
    },
    {
      "source": 25,
      "target": 127
    },
    {
      "source": 26,
      "target": 27
    },
    {
      "source": 26,
      "target": 28
    },
    {
      "source": 27,
      "target": 29
    },
    {
      "source": 27,
      "target": 33
    },
    {
      "source": 27,
      "target": 34
    },
    {
      "source": 28,
      "target": 33
    },
    {
      "source": 28,
      "target": 30
    },
    {
      "source": 28,
      "target": 34
    },
    {
      "source": 29,
      "target": 30
    },
    {
      "source": 29,
      "target": 31
    },
    {
      "source": 29,
      "target": 32
    },
    {
      "source": 29,
      "target": 35
    },
    {
      "source": 29,
      "target": 126
    },
    {
      "source": 30,
      "target": 33
    },
    {
      "source": 31,
      "target": 35
    },
    {
      "source": 31,
      "target": 61
    },
    {
      "source": 31,
      "target": 36
    },
    {
      "source": 31,
      "target": 71
    },
    {
      "source": 31,
      "target": 66
    },
    {
      "source": 31,
      "target": 69
    },
    {
      "source": 31,
      "target": 67
    },
    {
      "source": 31,
      "target": 62
    },
    {
      "source": 31,
      "target": 68
    },
    {
      "source": 31,
      "target": 72
    },
    {
      "source": 31,
      "target": 34
    },
    {
      "source": 31,
      "target": 40
    },
    {
      "source": 33,
      "target": 34
    },
    {
      "source": 35,
      "target": 36
    },
    {
      "source": 36,
      "target": 38
    },
    {
      "source": 37,
      "target": 38
    },
    {
      "source": 37,
      "target": 39
    },
    {
      "source": 37,
      "target": 40
    },
    {
      "source": 39,
      "target": 40
    },
    {
      "source": 39,
      "target": 70
    },
    {
      "source": 40,
      "target": 57
    },
    {
      "source": 41,
      "target": 42
    },
    {
      "source": 41,
      "target": 43
    },
    {
      "source": 41,
      "target": 44
    },
    {
      "source": 41,
      "target": 45
    },
    {
      "source": 41,
      "target": 46
    },
    {
      "source": 42,
      "target": 58
    },
    {
      "source": 42,
      "target": 59
    },
    {
      "source": 42,
      "target": 83
    },
    {
      "source": 42,
      "target": 45
    },
    {
      "source": 42,
      "target": 60
    },
    {
      "source": 42,
      "target": 44
    },
    {
      "source": 42,
      "target": 75
    },
    {
      "source": 42,
      "target": 73
    },
    {
      "source": 43,
      "target": 45
    },
    {
      "source": 43,
      "target": 108
    },
    {
      "source": 43,
      "target": 111
    },
    {
      "source": 43,
      "target": 112
    },
    {
      "source": 43,
      "target": 44
    },
    {
      "source": 43,
      "target": 58
    },
    {
      "source": 44,
      "target": 45
    },
    {
      "source": 44,
      "target": 115
    },
    {
      "source": 44,
      "target": 116
    },
    {
      "source": 45,
      "target": 83
    },
    {
      "source": 45,
      "target": 86
    },
    {
      "source": 45,
      "target": 48
    },
    {
      "source": 46,
      "target": 80
    },
    {
      "source": 46,
      "target": 75
    },
    {
      "source": 46,
      "target": 50
    },
    {
      "source": 47,
      "target": 48
    },
    {
      "source": 47,
      "target": 49
    },
    {
      "source": 47,
      "target": 50
    },
    {
      "source": 47,
      "target": 51
    },
    {
      "source": 47,
      "target": 52
    },
    {
      "source": 47,
      "target": 53
    },
    {
      "source": 47,
      "target": 54
    },
    {
      "source": 47,
      "target": 91
    },
    {
      "source": 48,
      "target": 83
    },
    {
      "source": 48,
      "target": 84
    },
    {
      "source": 49,
      "target": 105
    },
    {
      "source": 49,
      "target": 82
    },
    {
      "source": 50,
      "target": 52
    },
    {
      "source": 50,
      "target": 51
    },
    {
      "source": 50,
      "target": 54
    },
    {
      "source": 50,
      "target": 53
    },
    {
      "source": 51,
      "target": 53
    },
    {
      "source": 51,
      "target": 91
    },
    {
      "source": 52,
      "target": 54
    },
    {
      "source": 53,
      "target": 91
    },
    {
      "source": 53,
      "target": 109
    },
    {
      "source": 54,
      "target": 117
    },
    {
      "source": 55,
      "target": 56
    },
    {
      "source": 55,
      "target": 82
    },
    {
      "source": 56,
      "target": 73
    },
    {
      "source": 56,
      "target": 82
    },
    {
      "source": 57,
      "target": 58
    },
    {
      "source": 57,
      "target": 59
    },
    {
      "source": 58,
      "target": 59
    },
    {
      "source": 59,
      "target": 60
    },
    {
      "source": 60,
      "target": 73
    },
    {
      "source": 60,
      "target": 75
    },
    {
      "source": 60,
      "target": 74
    },
    {
      "source": 61,
      "target": 62
    },
    {
      "source": 61,
      "target": 63
    },
    {
      "source": 61,
      "target": 64
    },
    {
      "source": 62,
      "target": 106
    },
    {
      "source": 62,
      "target": 63
    },
    {
      "source": 62,
      "target": 95
    },
    {
      "source": 63,
      "target": 72
    },
    {
      "source": 63,
      "target": 69
    },
    {
      "source": 64,
      "target": 95
    },
    {
      "source": 64,
      "target": 71
    },
    {
      "source": 64,
      "target": 69
    },
    {
      "source": 65,
      "target": 66
    },
    {
      "source": 65,
      "target": 67
    },
    {
      "source": 65,
      "target": 68
    },
    {
      "source": 65,
      "target": 69
    },
    {
      "source": 66,
      "target": 67
    },
    {
      "source": 66,
      "target": 69
    },
    {
      "source": 66,
      "target": 68
    },
    {
      "source": 67,
      "target": 68
    },
    {
      "source": 67,
      "target": 69
    },
    {
      "source": 67,
      "target": 71
    },
    {
      "source": 68,
      "target": 69
    },
    {
      "source": 70,
      "target": 100
    },
    {
      "source": 71,
      "target": 106
    },
    {
      "source": 73,
      "target": 74
    },
    {
      "source": 73,
      "target": 75
    },
    {
      "source": 73,
      "target": 76
    },
    {
      "source": 74,
      "target": 75
    },
    {
      "source": 74,
      "target": 117
    },
    {
      "source": 74,
      "target": 112
    },
    {
      "source": 75,
      "target": 80
    },
    {
      "source": 76,
      "target": 82
    },
    {
      "source": 77,
      "target": 78
    },
    {
      "source": 77,
      "target": 79
    },
    {
      "source": 78,
      "target": 79
    },
    {
      "source": 78,
      "target": 125
    },
    {
      "source": 79,
      "target": 125
    },
    {
      "source": 79,
      "target": 129
    },
    {
      "source": 82,
      "target": 105
    },
    {
      "source": 83,
      "target": 84
    },
    {
      "source": 83,
      "target": 85
    },
    {
      "source": 83,
      "target": 86
    },
    {
      "source": 83,
      "target": 87
    },
    {
      "source": 83,
      "target": 88
    },
    {
      "source": 84,
      "target": 85
    },
    {
      "source": 85,
      "target": 100
    },
    {
      "source": 86,
      "target": 87
    },
    {
      "source": 87,
      "target": 88
    },
    {
      "source": 88,
      "target": 96
    },
    {
      "source": 89,
      "target": 90
    },
    {
      "source": 89,
      "target": 91
    },
    {
      "source": 89,
      "target": 107
    },
    {
      "source": 90,
      "target": 91
    },
    {
      "source": 90,
      "target": 107
    },
    {
      "source": 91,
      "target": 109
    },
    {
      "source": 91,
      "target": 92
    },
    {
      "source": 92,
      "target": 93
    },
    {
      "source": 92,
      "target": 94
    },
    {
      "source": 93,
      "target": 94
    },
    {
      "source": 93,
      "target": 110
    },
    {
      "source": 94,
      "target": 110
    },
    {
      "source": 96,
      "target": 98
    },
    {
      "source": 97,
      "target": 98
    },
    {
      "source": 97,
      "target": 99
    },
    {
      "source": 98,
      "target": 99
    },
    {
      "source": 99,
      "target": 120
    },
    {
      "source": 99,
      "target": 121
    },
    {
      "source": 99,
      "target": 130
    },
    {
      "source": 99,
      "target": 122
    },
    {
      "source": 99,
      "target": 131
    },
    {
      "source": 99,
      "target": 132
    },
    {
      "source": 99,
      "target": 133
    },
    {
      "source": 99,
      "target": 134
    },
    {
      "source": 99,
      "target": 135
    },
    {
      "source": 101,
      "target": 102
    },
    {
      "source": 101,
      "target": 103
    },
    {
      "source": 101,
      "target": 104
    },
    {
      "source": 103,
      "target": 104
    },
    {
      "source": 107,
      "target": 118
    },
    {
      "source": 107,
      "target": 119
    },
    {
      "source": 108,
      "target": 111
    },
    {
      "source": 108,
      "target": 114
    },
    {
      "source": 109,
      "target": 110
    },
    {
      "source": 111,
      "target": 117
    },
    {
      "source": 111,
      "target": 121
    },
    {
      "source": 111,
      "target": 112
    },
    {
      "source": 112,
      "target": 117
    },
    {
      "source": 114,
      "target": 115
    },
    {
      "source": 118,
      "target": 119
    },
    {
      "source": 118,
      "target": 120
    },
    {
      "source": 118,
      "target": 121
    },
    {
      "source": 118,
      "target": 122
    },
    {
      "source": 119,
      "target": 130
    },
    {
      "source": 120,
      "target": 130
    },
    {
      "source": 120,
      "target": 122
    },
    {
      "source": 120,
      "target": 132
    },
    {
      "source": 120,
      "target": 133
    },
    {
      "source": 121,
      "target": 130
    },
    {
      "source": 121,
      "target": 132
    },
    {
      "source": 121,
      "target": 133
    },
    {
      "source": 122,
      "target": 130
    },
    {
      "source": 122,
      "target": 131
    },
    {
      "source": 122,
      "target": 134
    },
    {
      "source": 122,
      "target": 135
    },
    {
      "source": 122,
      "target": 133
    },
    {
      "source": 123,
      "target": 124
    },
    {
      "source": 123,
      "target": 125
    },
    {
      "source": 125,
      "target": 129
    },
    {
      "source": 125,
      "target": 137
    },
    {
      "source": 127,
      "target": 128
    },
    {
      "source": 129,
      "target": 137
    },
    {
      "source": 130,
      "target": 131
    },
    {
      "source": 130,
      "target": 134
    },
    {
      "source": 130,
      "target": 133
    },
    {
      "source": 130,
      "target": 135
    },
    {
      "source": 131,
      "target": 132
    },
    {
      "source": 131,
      "target": 133
    },
    {
      "source": 131,
      "target": 134
    },
    {
      "source": 131,
      "target": 135
    },
    {
      "source": 132,
      "target": 133
    },
    {
      "source": 132,
      "target": 135
    },
    {
      "source": 132,
      "target": 134
    },
    {
      "source": 133,
      "target": 135
    },
    {
      "source": 133,
      "target": 134
    },
    {
      "source": 134,
      "target": 135
    },
    {
      "source": 135,
      "target": 136
    }
  ]
}